[{"created_at":"19\/11 16:11:34","message":"Mais cinco universidades portuguesas aceitam o #Enem -\nhttps:\/\/t.co\/PPnT2PZOtf","user_id":61022447,"user":"mundoeducacao","name":"Mundo Educa\u00e7\u00e3o","location":"Brasil","image":"http:\/\/pbs.twimg.com\/profile_images\/1014591901767557120\/GpEQmOVo_normal.jpg"},{"created_at":"19\/11 16:11:34","message":"Mais cinco universidades portuguesas aceitam o #Enem -\nhttps:\/\/t.co\/PPnT2PZOtf","user_id":61022447,"user":"mundoeducacao","name":"Mundo Educa\u00e7\u00e3o","location":"Brasil","image":"http:\/\/pbs.twimg.com\/profile_images\/1014591901767557120\/GpEQmOVo_normal.jpg"},{"created_at":"19\/11 16:12:49","message":"@g1educacao #Enem obg por anular uma das poucas quest\u00f5es que acertei \ud83d\ude44\ud83d\ude05","user_id":3331327397,"user":"HellenS45304197","name":"Hellen Souza","location":"Jord\u00e2nia, Brasil","image":"http:\/\/pbs.twimg.com\/profile_images\/999357591825170432\/JxMSvsVJ_normal.jpg"},{"created_at":"19\/11 16:12:49","message":"@g1educacao #Enem obg por anular uma das poucas quest\u00f5es que acertei \ud83d\ude44\ud83d\ude05","user_id":3331327397,"user":"HellenS45304197","name":"Hellen Souza","location":"Jord\u00e2nia, Brasil","image":"http:\/\/pbs.twimg.com\/profile_images\/999357591825170432\/JxMSvsVJ_normal.jpg"},{"tweet_image":"http:\/\/pbs.twimg.com\/media\/EIZKG92XUAAllg5.jpg","created_at":"19\/11 16:20:25","message":"RT @xpintolino: #enem chegando  \ud83d\ude08\ud83d\ude08\ud83d\ude08\ud83e\udd70\u2764\u2764 https:\/\/t.co\/vSlF09lfUM","user_id":1.1535441661080084e+18,"user":"HunkboyFlorida","name":"Hunkboy","location":null,"image":"http:\/\/pbs.twimg.com\/profile_images\/1153544367430352896\/l1tcneQt_normal.jpg"},{"tweet_image":"http:\/\/pbs.twimg.com\/media\/EIZKG92XUAAllg5.jpg","created_at":"19\/11 16:20:25","message":"RT @xpintolino: #enem chegando  \ud83d\ude08\ud83d\ude08\ud83d\ude08\ud83e\udd70\u2764\u2764 https:\/\/t.co\/vSlF09lfUM","user_id":1.1535441661080084e+18,"user":"HunkboyFlorida","name":"Hunkboy","location":null,"image":"http:\/\/pbs.twimg.com\/profile_images\/1153544367430352896\/l1tcneQt_normal.jpg"},{"created_at":"19\/11 16:45:00","message":"A Bahiana \u00e9 pra voc\u00ea. Ainda d\u00e1 tempo de se inscrever e usar a sua nota do #ENEM para fazer parte da melhor escola d\u2026 https:\/\/t.co\/q5XkUPekDI","user_id":82225770,"user":"escolabahiana","name":"BAHIANA","location":"Salvador - Bahia - Brasil","image":"http:\/\/pbs.twimg.com\/profile_images\/1194594160797503489\/2lLmikVp_normal.png"},{"created_at":"19\/11 16:45:00","message":"A Bahiana \u00e9 pra voc\u00ea. Ainda d\u00e1 tempo de se inscrever e usar a sua nota do #ENEM para fazer parte da melhor escola d\u2026 https:\/\/t.co\/q5XkUPekDI","user_id":82225770,"user":"escolabahiana","name":"BAHIANA","location":"Salvador - Bahia - Brasil","image":"http:\/\/pbs.twimg.com\/profile_images\/1194594160797503489\/2lLmikVp_normal.png"},{"created_at":"19\/11 16:46:17","message":"Download via drive: https:\/\/t.co\/Y4Oifb7vmt\n#geometriaetrigonometria #enemnaeradigital #enem #matematica #geometria\u2026 https:\/\/t.co\/SrwgYdqm1U","user_id":1.1047887121546772e+18,"user":"geometrias2019","name":"Geometrias2019","location":null,"image":"http:\/\/pbs.twimg.com\/profile_images\/1144272524156579840\/SsGwpsTT_normal.png"},{"created_at":"19\/11 16:46:17","message":"Download via drive: https:\/\/t.co\/Y4Oifb7vmt\n#geometriaetrigonometria #enemnaeradigital #enem #matematica #geometria\u2026 https:\/\/t.co\/SrwgYdqm1U","user_id":1.1047887121546772e+18,"user":"geometrias2019","name":"Geometrias2019","location":null,"image":"http:\/\/pbs.twimg.com\/profile_images\/1144272524156579840\/SsGwpsTT_normal.png"},{"created_at":"19\/11 16:50:26","message":"Mais 5 universidades portuguesas aceitam o Enem; total sobe para 47 #enem https:\/\/t.co\/xg0GndxAgJ","user_id":29274419,"user":"otempo","name":"O Tempo","location":"Contagem \/ MG","image":"http:\/\/pbs.twimg.com\/profile_images\/1181230601925545984\/bRi4u9hZ_normal.jpg"},{"created_at":"19\/11 16:50:26","message":"Mais 5 universidades portuguesas aceitam o Enem; total sobe para 47 #enem https:\/\/t.co\/xg0GndxAgJ","user_id":29274419,"user":"otempo","name":"O Tempo","location":"Contagem \/ MG","image":"http:\/\/pbs.twimg.com\/profile_images\/1181230601925545984\/bRi4u9hZ_normal.jpg"},{"created_at":"19\/11 16:51:47","message":"RT @otempo: Mais 5 universidades portuguesas aceitam o Enem; total sobe para 47 #enem https:\/\/t.co\/xg0GndxAgJ","user_id":9.437850303877161e+17,"user":"Michelleengenha","name":"Michelle Fernandes","location":"Jo\u00e3o Monlevade, Brasil","image":"http:\/\/pbs.twimg.com\/profile_images\/1196586574168891393\/ETe2NBD2_normal.jpg"},{"created_at":"19\/11 16:51:47","message":"RT @otempo: Mais 5 universidades portuguesas aceitam o Enem; total sobe para 47 #enem https:\/\/t.co\/xg0GndxAgJ","user_id":9.437850303877161e+17,"user":"Michelleengenha","name":"Michelle Fernandes","location":"Jo\u00e3o Monlevade, Brasil","image":"http:\/\/pbs.twimg.com\/profile_images\/1196586574168891393\/ETe2NBD2_normal.jpg"},{"created_at":"19\/11 17:12:39","message":"RT @FEIonline: Boliche com bola de concreto feito pela Engenharia Civil da FEI \ud83c\udfb3\n\n#FEI #Engenharia #BomDia #RT #Vestibular #Desafio #ENEM h\u2026","user_id":298454982,"user":"Prof_BarretoFEI","name":"Prof.Marco.Barreto","location":"Sao Paulo, Brazil","image":"http:\/\/pbs.twimg.com\/profile_images\/1104558319967055872\/MLotYXIV_normal.jpg"},{"created_at":"19\/11 17:12:39","message":"RT @FEIonline: Boliche com bola de concreto feito pela Engenharia Civil da FEI \ud83c\udfb3\n\n#FEI #Engenharia #BomDia #RT #Vestibular #Desafio #ENEM h\u2026","user_id":298454982,"user":"Prof_BarretoFEI","name":"Prof.Marco.Barreto","location":"Sao Paulo, Brazil","image":"http:\/\/pbs.twimg.com\/profile_images\/1104558319967055872\/MLotYXIV_normal.jpg"},{"created_at":"19\/11 17:40:16","message":"#Inep anuncia cancelamento de uma quest\u00e3o do #Enem https:\/\/t.co\/7G9x7Z4J4V #educa\u00e7\u00e3o","user_id":9.286491822352835e+17,"user":"ODiarioCarioca","name":"Di\u00e1rio Carioca","location":"Rio de Janeiro, Brasil","image":"http:\/\/pbs.twimg.com\/profile_images\/1046823971918946309\/m0zrN3go_normal.jpg"},{"created_at":"19\/11 17:40:16","message":"#Inep anuncia cancelamento de uma quest\u00e3o do #Enem https:\/\/t.co\/7G9x7Z4J4V #educa\u00e7\u00e3o","user_id":9.286491822352835e+17,"user":"ODiarioCarioca","name":"Di\u00e1rio Carioca","location":"Rio de Janeiro, Brasil","image":"http:\/\/pbs.twimg.com\/profile_images\/1046823971918946309\/m0zrN3go_normal.jpg"},{"created_at":"19\/11 17:58:58","message":"Estudando para ENEM e vestibulares na https:\/\/t.co\/UKwP0tb4Lv - quest\u00f5es, provas, simulados e reda\u00e7\u00e3o #estudacom #enem","user_id":9.956908408519926e+17,"user":"LuisArthurLobo","name":"\ud835\udd43\ud835\udd4c\ud835\udd3b\ud835\udd40","location":"Bras\u00edlia, Brasil","image":"http:\/\/pbs.twimg.com\/profile_images\/1165667703534886913\/R3QjoEVI_normal.jpg"},{"created_at":"19\/11 17:58:58","message":"Estudando para ENEM e vestibulares na https:\/\/t.co\/UKwP0tb4Lv - quest\u00f5es, provas, simulados e reda\u00e7\u00e3o #estudacom #enem","user_id":9.956908408519926e+17,"user":"LuisArthurLobo","name":"\ud835\udd43\ud835\udd4c\ud835\udd3b\ud835\udd40","location":"Bras\u00edlia, Brasil","image":"http:\/\/pbs.twimg.com\/profile_images\/1165667703534886913\/R3QjoEVI_normal.jpg"}]