[{"created_at":"24\/01 20:53:38","message":"RT @noahakilahrosa: To ficando doente ADIA ENEM ULTIMATO","user_id":1.3493122969092137e+18,"user":"noahakilahrosa","name":"NoahAkilahRS","location":null,"image":"http:\/\/pbs.twimg.com\/profile_images\/1350243196643717122\/y7fkN72g_normal.jpg"},{"created_at":"24\/01 20:53:49","message":"RT @noahakilahrosa: ADIA ENEM ULTIMATO \nADIA ENEM ULTIMATO \nADIA ENEM ULTIMATO \nADIA ENEM ULTIMATO","user_id":1.3493122969092137e+18,"user":"noahakilahrosa","name":"NoahAkilahRS","location":null,"image":"http:\/\/pbs.twimg.com\/profile_images\/1350243196643717122\/y7fkN72g_normal.jpg"},{"created_at":"24\/01 21:55:43","message":"Se adiar o ENEM adia o recebimento da propina.","user_id":1.3522304682095534e+18,"user":"Renan42985109","name":"Renan","location":null,"image":"http:\/\/pbs.twimg.com\/profile_images\/1352237489151500288\/jh_VFbCz_normal.jpg"},{"created_at":"24\/01 22:26:06","message":"Velho eu fico indignado com o palco que voc\u00eas d\u00e3o para esse tipo de pessoa a mina milita escrevendo adia enem no IP\u2026 https:\/\/t.co\/FI3y8SMUOl","user_id":1.318902479636095e+18,"user":"Guilhermee_mn","name":"Guigo","location":"Porto Alegre, Brasil","image":"http:\/\/pbs.twimg.com\/profile_images\/1353152264492474369\/HSmROEJB_normal.jpg"},{"created_at":"24\/01 23:47:27","message":"ADIA ENEM ULTIMATO","user_id":1.0603708584458117e+18,"user":"sobrino_bruno","name":"supino","location":null,"image":"http:\/\/pbs.twimg.com\/profile_images\/1297656500580753408\/B-ey15n4_normal.jpg"},{"created_at":"25\/01 10:19:50","message":"RT @igormageskifad: Hj \u00e9 o \u00fanico dia q vc pode dar rt neste patrim\u00f4nio brasileiro:\n#Enem2020 #euvoudeproenem ADIA ENEM ULTIMATO https:\/\/t.c\u2026","user_id":1.280654588249596e+18,"user":"btsletknow","name":"ANA","location":"ONLY ARMY","image":"http:\/\/pbs.twimg.com\/profile_images\/1349478935801769984\/HF_RjJsr_normal.jpg"},{"created_at":"25\/01 11:03:34","message":"nas quartas usamos rosa e pedimos adia enem \ud83c\udf39\ud83d\udc5a","user_id":8.001390785701642e+17,"user":"perrynvogue","name":"lipe","location":null,"image":"http:\/\/pbs.twimg.com\/profile_images\/1347711367231508480\/2FBofZxP_normal.jpg"},{"tweet_image":"http:\/\/pbs.twimg.com\/media\/ErswBGqUcAAGSRr.jpg","created_at":"25\/01 22:12:22","message":"RT @shotoword: os estudantes: ADIA ENEM 2020\n\nO MEC: https:\/\/t.co\/Yt9mDbX1zI","user_id":1.3411459202897797e+18,"user":"Peachinlov","name":"Vita\ud83c\udf38","location":null,"image":"http:\/\/pbs.twimg.com\/profile_images\/1341147590600101890\/8W8v_4Cq_normal.jpg"},{"tweet_image":"http:\/\/pbs.twimg.com\/media\/ErswBGqUcAAGSRr.jpg","created_at":"25\/01 22:13:56","message":"RT @shotoword: os estudantes: ADIA ENEM 2020\n\nO MEC: https:\/\/t.co\/Yt9mDbX1zI","user_id":1.3096911462480978e+18,"user":"lovesquadbot","name":"\ud83c\udf31\ud835\udcd5\ud835\udcfb\ud835\udcea\ud835\udcf7\ud835\udcec\ud835\udd02\ud835\udcfc \ud83d\udc38 \u2014 (secund\u00e1ria)","location":"\ud83c\udfe1:: Adrinette \ud80c\udc83\u2665\ufe0e\n","image":"http:\/\/pbs.twimg.com\/profile_images\/1347734931657601031\/rzCGPLYu_normal.jpg"},{"created_at":"27\/01 17:55:11","message":"n\u00e3o adianta nada vcs falarem adia enem e fora bsonaro e chamar uma pessoa com um debate social importante e com um\u2026 https:\/\/t.co\/rCxcERKU9Z","user_id":1.3363923844526367e+18,"user":"tuitamad","name":"madu","location":null,"image":"http:\/\/pbs.twimg.com\/profile_images\/1350925682679963649\/pt49IAD-_normal.jpg"},{"created_at":"27\/01 17:56:02","message":"RT @tuitamad: n\u00e3o adianta nada vcs falarem adia enem e fora bsonaro e chamar uma pessoa com um debate social importante e com um ponto real\u2026","user_id":1.3526341905761526e+18,"user":"itsickyvicky","name":"ickyvicky","location":null,"image":"http:\/\/pbs.twimg.com\/profile_images\/1352637441082011648\/Goa2K_M9_normal.jpg"},{"created_at":"27\/01 17:56:28","message":"RT @tuitamad: n\u00e3o adianta nada vcs falarem adia enem e fora bsonaro e chamar uma pessoa com um debate social importante e com um ponto real\u2026","user_id":30503927,"user":"claratuitera","name":"clara","location":"comunadyke","image":"http:\/\/pbs.twimg.com\/profile_images\/1354228679837102083\/_T8c__2u_normal.jpg"},{"created_at":"27\/01 21:53:37","message":"sei la eu acho meio chato sabe pediu adia enem por causa do corona mas vai ir pra festa com 70, 80 pessoas sei la sabe","user_id":7.019251468656271e+17,"user":"sabrinabsana","name":"sa","location":"SC","image":"http:\/\/pbs.twimg.com\/profile_images\/1353830151818194945\/GO5_Gowa_normal.jpg"},{"created_at":"28\/01 09:55:51","message":"RT @tuitamad: n\u00e3o adianta nada vcs falarem adia enem e fora bsonaro e chamar uma pessoa com um debate social importante e com um ponto real\u2026","user_id":1.3037623477571133e+18,"user":"realitiesfavs","name":"\u05b4\u05b6\u05b8","location":"fan account","image":"http:\/\/pbs.twimg.com\/profile_images\/1354623992649363456\/uSZNHy-b_normal.jpg"},{"created_at":"28\/01 15:55:30","message":"@cazawres ADIA ENEM","user_id":1.3290987880871485e+18,"user":"sonsccp","name":"\u2326\ud835\ude8b\ud835\ude8e\ud835\ude8a","location":"\ud83c\udde6\ud83c\uddf4","image":"http:\/\/pbs.twimg.com\/profile_images\/1354322974741045249\/1MtIJAfF_normal.jpg"},{"created_at":"28\/01 19:32:11","message":"enem e elei\u00e7\u00e3o ngm adia n\u00e9 KKKKKK","user_id":8.087980224318628e+17,"user":"pascoal_lucca","name":"Lucca Pascoal \ud83d\udc4b\ud83c\udffd\u26bd\ufe0f","location":"Campinas, Brasil","image":"http:\/\/pbs.twimg.com\/profile_images\/1345151148420902919\/lcJOKaqm_normal.jpg"},{"created_at":"28\/01 21:43:11","message":"RT @fabiayasmim_: ADIA ENEM JUSTI\u00c7A","user_id":1.2642665300381286e+18,"user":"fabiayasmim_","name":"doidinha de Jesus","location":"Maranh\u00e3o, Brasil","image":"http:\/\/pbs.twimg.com\/profile_images\/1278513961793654784\/AVC7RfBW_normal.jpg"},{"created_at":"08\/02 20:20:02","message":"RT @igormageskifad: Hj \u00e9 o \u00fanico dia q vc pode dar rt neste patrim\u00f4nio brasileiro:\n#Enem2020 #euvoudeproenem ADIA ENEM ULTIMATO https:\/\/t.c\u2026","user_id":1.1797947797119508e+18,"user":"Magali_Surtada","name":"\ud835\udc9f\ud835\udc5c\ud835\udc50\ud835\udc56\ud835\udc5b\u210e\ud835\udc5c\ud83c\udf19","location":"Via L\u00e1ctea","image":"http:\/\/pbs.twimg.com\/profile_images\/1305951958562492417\/GHEuv0oY_normal.jpg"},{"created_at":"08\/02 20:22:02","message":"RT @igormageskifad: Hj \u00e9 o \u00fanico dia q vc pode dar rt neste patrim\u00f4nio brasileiro:\n#Enem2020 #euvoudeproenem ADIA ENEM ULTIMATO https:\/\/t.c\u2026","user_id":1.2952434003845202e+18,"user":"quackboot","name":"QUACK BR","location":null,"image":"http:\/\/pbs.twimg.com\/profile_images\/1346535729736933379\/Y6lExRWM_normal.jpg"},{"created_at":"08\/04 12:03:04","message":"RT @igormageskifad: Hj \u00e9 o \u00fanico dia q vc pode dar rt neste patrim\u00f4nio brasileiro:\n#Enem2020 #euvoudeproenem ADIA ENEM ULTIMATO https:\/\/t.c\u2026","user_id":1.3082066217352356e+18,"user":"baegurt","name":"\ud835\udd91\ud835\udd8e\ud835\udd86. rt no fix hehe","location":null,"image":"http:\/\/pbs.twimg.com\/profile_images\/1368076042922037250\/PwJc9hL5_normal.jpg"}]